{"skeleton":{"hash":"bsZWTBZRfSI","spine":"4.2.43","x":-121.81,"y":-41.83,"width":270.65,"height":725.5,"images":"./images/","audio":"./audio"},"bones":[{"name":"root"},{"name":"all","parent":"root","x":-477.11,"y":51.46},{"name":"treeR_all","parent":"all","x":481.69,"y":-61.59},{"name":"treeR_than","parent":"treeR_all","length":92.75,"rotation":89.43,"x":-1.09,"y":4.81},{"name":"treeR_leaf","parent":"treeR_than","length":172.3,"rotation":2.04,"x":80,"y":0.11},{"name":"treeR_leaf2","parent":"treeR_leaf","length":153.49,"rotation":-0.64,"x":172.3},{"name":"treeR_leaf3","parent":"treeR_leaf2","length":133.62,"rotation":0.12,"x":153.49},{"name":"treeR_leaf4","parent":"treeR_leaf3","length":83.28,"rotation":5.14,"x":133.62},{"name":"treeR_leaf5","parent":"treeR_leaf4","length":71.52,"rotation":2.79,"x":83.28},{"name":"treeR_sd","parent":"treeR_all","x":-16.39,"y":5.3}],"slots":[{"name":"treeR_sd","bone":"treeR_sd","attachment":"tree/treeR_sd"},{"name":"treeR_than","bone":"treeR_than","attachment":"tree/treeR_than"},{"name":"treeR_leaf","bone":"treeR_leaf","attachment":"tree/treeR_leaf"}],"skins":[{"name":"default","attachments":{"treeR_leaf":{"tree/treeR_leaf":{"type":"mesh","uvs":[0.34072,0.08456,0.42874,0.18736,0.51677,0.29015,0.55911,0.47799,0.60144,0.66583,0.48659,0.84118,0.27114,0.90056,0.05906,0.83357,0,0.64492,0,0.44726,0.05904,0.30418,0.10916,0.18274,0.14672,0.09173,0.18428,7.2E-4,0.2691,9.4E-4],"triangles":[12,14,0,12,13,14,1,11,0,11,12,0,3,10,2,10,1,2,10,11,1,9,10,3,3,8,9,6,7,5,4,5,8,8,5,7,4,8,3],"vertices":[2,7,86.96,-45.67,0.56257,8,1.45,-45.79,0.43743,3,6,152.13,-76.11,0.26298,7,11.62,-77.47,0.73685,8,-75.35,-73.88,1.6E-4,4,4,404.68,-116.99,5.8E-4,5,233.68,-114.37,0.06546,6,79.94,-114.54,0.75143,7,-63.72,-109.27,0.18253,4,4,273.5,-132.68,0.15408,5,102.69,-131.53,0.64565,6,-51.09,-131.43,0.19854,7,-195.74,-114.34,0.00173,3,4,142.32,-148.38,0.77541,5,-28.31,-148.7,0.22435,6,-182.12,-148.31,2.4E-4,2,4,21.64,-93.58,0.99988,5,-149.6,-95.27,1.2E-4,1,4,-17.19,4.4,1,1,4,31.87,98.61,1,3,4,163.8,121.81,0.63163,5,-9.87,121.71,0.36701,6,-163.1,122.06,0.00136,3,4,301.34,118.29,0.01696,5,127.69,119.73,0.67447,6,-25.54,119.78,0.30857,3,5,226.88,91.73,0.09192,6,73.58,91.57,0.88425,7,-51.59,96.58,0.02382,3,6,157.72,67.63,0.31224,7,30.07,65.19,0.68183,8,-49.98,67.71,0.00593,3,6,220.78,49.68,0.00284,7,91.26,41.67,0.42202,8,10,41.23,0.57514,1,8,69.98,14.75,1,1,8,63.93,-22.94,1],"hull":15,"edges":[8,10,10,12,12,14,14,16,16,18,26,28,4,6,6,8,18,20,20,22,22,24,24,26,0,28,0,2,2,4],"width":450,"height":696}},"treeR_sd":{"tree/treeR_sd":{"width":204,"height":74}},"treeR_than":{"tree/treeR_than":{"x":60.89,"y":10.89,"rotation":-89.43,"width":118,"height":139}}}}],"animations":{"idle":{"bones":{"treeR_leaf":{"rotate":[{"curve":[0.333,0,0.667,1.13]},{"time":1,"value":1.13,"curve":[1.333,1.13,1.667,0]},{"time":2}]},"treeR_leaf2":{"rotate":[{"value":0.09,"curve":[0.058,0.04,0.112,0]},{"time":0.1667,"curve":[0.5,0,0.833,1.13]},{"time":1.1667,"value":1.13,"curve":[1.446,1.13,1.724,0.35]},{"time":2,"value":0.09}]},"treeR_leaf3":{"rotate":[{"value":0.3,"curve":[0.113,0.13,0.223,0]},{"time":0.3333,"curve":[0.667,0,1,1.13]},{"time":1.3333,"value":1.13,"curve":[1.557,1.13,1.78,0.63]},{"time":2,"value":0.3}]},"treeR_leaf4":{"rotate":[{"value":2.37,"curve":[0.169,1.19,0.334,0]},{"time":0.5,"curve":[0.833,0,1.167,4.74]},{"time":1.5,"value":4.74,"curve":[1.668,4.74,1.836,3.56]},{"time":2,"value":2.37}]},"treeR_leaf5":{"rotate":[{"value":3.5,"curve":[0.224,2.1,0.446,0]},{"time":0.6667,"curve":[1,0,1.333,4.74]},{"time":1.6667,"value":4.74,"curve":[1.779,4.74,1.891,4.22]},{"time":2,"value":3.5}]}}}}}